<?xml version="1.0" encoding="UTF-8"?>
<objects serializationModel="Studio.02.02.00">
	<object class="AudioFile" id="{f16cf1a1-4361-4a8c-a5a8-0c94f6a5240a}">
		<property name="assetPath">
			<value>SFX/Explosion/explosion01.mp3</value>
		</property>
		<property name="frequencyInKHz">
			<value>48</value>
		</property>
		<property name="channelCount">
			<value>2</value>
		</property>
		<property name="length">
			<value>5.6879999999999997</value>
		</property>
		<relationship name="masterAssetFolder">
			<destination>{ba1157a2-665a-4d29-8673-38a9d4cd6fe0}</destination>
		</relationship>
	</object>
</objects>
